configj/__init__.py
configj/abstract_config.py
configj/configj.py
ConfigJ-1.0.0.dist-info/METADATA
ConfigJ-1.0.0.dist-info/WHEEL
ConfigJ-1.0.0.dist-info/top_level.txt
ConfigJ-1.0.0.dist-info/RECORD
