Metadata-Version: 2.1
Name: ConfigJ
Version: 1.0.0
Summary: A json base config lib.
Home-page: https://github.com/DancingSnow0517/ConfigJ
Author: DancingSnow
Author-email: 1121149616@qq.com
Project-URL: Bug Tracker, https://github.com/DancingSnow0517/ConfigJ/issues
Classifier: Programming Language :: Python :: 3
Classifier: License :: OSI Approved :: MIT License
Classifier: Operating System :: OS Independent
Requires-Python: >=3.6
